persistent_bm25/__init__.py
persistent_bm25/retriever.py
persistent_bm25-0.4.dist-info/METADATA
persistent_bm25-0.4.dist-info/WHEEL
persistent_bm25-0.4.dist-info/top_level.txt
persistent_bm25-0.4.dist-info/RECORD
