Metadata-Version: 2.2
Name: persistent_bm25
Version: 0.4
Summary: A persistent implementation of BM25 retrieval.
Home-page: https://github.com/mohammed-orabi2/persistent-bm25
Author: Mohammed Orabi
Author-email: mahmedorabi297@gmail.com
Classifier: Programming Language :: Python :: 3
Classifier: License :: OSI Approved :: MIT License
Classifier: Operating System :: OS Independent
Requires-Python: >=3.7
Requires-Dist: langchain
Requires-Dist: rank_bm25
Dynamic: author
Dynamic: author-email
Dynamic: classifier
Dynamic: description
Dynamic: description-content-type
Dynamic: home-page
Dynamic: requires-dist
Dynamic: requires-python
Dynamic: summary
